<?xml version="1.0" encoding="utf-8" ?>
<widget id="WidgetName.widget.WidgetName" needsEntityContext="true" xmlns="http://www.mendix.com/widget/1.0/">
    <name>WidgetName</name>
    <description>The description of this widget.</description>

    <icon />

    <properties>
        <property key="targetGraph" type="string" required="false" defaultValue="">
            <caption>Render graph</caption>
            <category>Behavior</category>
            <description>Render graphs for target application </description>
        </property>
    </properties>
</widget>

